alembic_viz/__init__.py
alembic_viz/alembic_viz.py
alembic_viz/utils.py
alembic_viz-0.1.0.dist-info/DESCRIPTION.rst
alembic_viz-0.1.0.dist-info/METADATA
alembic_viz-0.1.0.dist-info/RECORD
alembic_viz-0.1.0.dist-info/WHEEL
alembic_viz-0.1.0.dist-info/entry_points.txt
alembic_viz-0.1.0.dist-info/metadata.json
alembic_viz-0.1.0.dist-info/pbr.json
alembic_viz-0.1.0.dist-info/top_level.txt
