Metadata-Version: 2.0
Name: alembic-viz
Version: 0.1.0
Summary: Graph Visualization of Alembic Migrations
Home-page: UNKNOWN
Author: Jan van Esdonk
Author-email: dev@vanesdonk.de
License: UNKNOWN
Platform: UNKNOWN
Classifier: Environment :: Console
Classifier: Intended Audience :: Developers
Classifier: Operating System :: POSIX :: Linux
Classifier: Programming Language :: Python
Classifier: Topic :: Software Development Libraries
Requires-Dist: Mako (==1.0.5)
Requires-Dist: MarkupSafe (==0.23)
Requires-Dist: SQLAlchemy (==1.1.3)
Requires-Dist: alembic (==0.8.8)
Requires-Dist: click (==6.6)
Requires-Dist: graphviz (==0.5.1)
Requires-Dist: python-editor (==1.0.1)
